rformat/__init__.py
rformat/resultset.py
rformat/utils/__init__.py
rformat/utils/bench.py
rformat/utils/config.py
rsformat-0.0.1.dist-info/METADATA
rsformat-0.0.1.dist-info/RECORD
rsformat-0.0.1.dist-info/WHEEL
rsformat-0.0.1.dist-info/top_level.txt
