Metadata-Version: 2.1
Name: rsformat
Version: 0.0.1
Summary: Record set formatter
Home-page: https://www.qsonlabs.com
Author: Chris O'Connor
Author-email: cdoconno@gmail.com
License: Apache
Platform: UNKNOWN
Classifier: License :: OSI Approved :: Apache Software License
Classifier: Operating System :: OS Independent
Classifier: Programming Language :: Python :: 2.7
